api_resources/__init__.py
api_resources/course.py
api_resources/abstract/__init__.py
api_resources/abstract/api_resource.py
api_resources/abstract/listable_api_resource.py
api_resources/abstract/retrievable_api_resource.py
learndash/__init__.py
learndash/api_requestor.py
learndash/exceptions.py
learndash/api_resources/__init__.py
learndash/api_resources/course.py
learndash/api_resources/typing.py
learndash/api_resources/user.py
learndash/api_resources/abstract/__init__.py
learndash/api_resources/abstract/api_resource.py
learndash/api_resources/abstract/listable_api_resource.py
learndash/api_resources/abstract/nested_api_resource.py
learndash/api_resources/abstract/retrievable_api_resource.py
learndash/api_resources/abstract/updateable_api_resource.py
learndash-0.0.7.dist-info/LICENSE
learndash-0.0.7.dist-info/METADATA
learndash-0.0.7.dist-info/WHEEL
learndash-0.0.7.dist-info/top_level.txt
learndash-0.0.7.dist-info/RECORD
