Metadata-Version: 2.1
Name: learndash
Version: 0.0.7
Summary: A python wrapper for a LearnDash API
Home-page: https://github.com/buildnode/learndash-python
Author: Jorgen Hookham
Author-email: jorgen@buildnode.io
License: UNKNOWN
Project-URL: Bug Tracker, https://github.com/buildnode/learndash-python/issues
Platform: UNKNOWN
Classifier: Programming Language :: Python :: 3
Classifier: License :: OSI Approved :: MIT License
Classifier: Operating System :: OS Independent
Requires-Python: >=3.6
Requires-Dist: requests
